README.rst
bowyer/_meta/smoketest.cfg.yaml
bowyer/_meta/spec_bowyer.py
bowyer/cfg/__init__.py
bowyer/cfg/_meta/conftest.py
bowyer/cfg/_meta/spec_bowyer_cfg.py
bowyer/cfg/_meta/spec_bowyer_cfg_builder.py
bowyer/cfg/_meta/spec_bowyer_cfg_edge.py
bowyer/cfg/_meta/spec_bowyer_cfg_load.py
bowyer/cfg/_meta/spec_bowyer_cfg_override.py
bowyer/cfg/_meta/spec_bowyer_cfg_util.py
bowyer/cfg/_meta/spec_bowyer_cfg_validate.py
bowyer/cfg/builder.py
bowyer/cfg/data/__init__.py
bowyer/cfg/data/_meta/conftest.py
bowyer/cfg/data/_meta/spec_bowyer_cfg_data.py
bowyer/cfg/data/_meta/spec_bowyer_cfg_data_atomic_types.py
bowyer/cfg/data/_meta/spec_bowyer_cfg_data_gap_table.py
bowyer/cfg/data/atomic_types.py
bowyer/cfg/data/gap_table.py
bowyer/cfg/edge.py
bowyer/cfg/exception.py
bowyer/cfg/load.py
bowyer/cfg/override.py
bowyer/cfg/queue.py
bowyer/cfg/util.py
bowyer/cfg/validate.py
bowyer/cli/__init__.py
bowyer/cli/command.py
bowyer/cli/util.py
bowyer/exception/__init__.py
bowyer/exception/_meta/spec_bowyer_exception.py
bowyer/gen/__init__.py
bowyer/gen/_meta/spec_bowyer_gen.py
bowyer/gen/_meta/spec_bowyer_gen_python.py
bowyer/gen/python.py
bowyer/host/__init__.py
bowyer/host/_meta/spec_bowyer_host.py
bowyer/host/_meta/spec_bowyer_host_remote.py
bowyer/host/util.py
bowyer/lib/test/native/native_controller.pyx
bowyer/lib/test/native/native_printer.pyx
bowyer/log/__init__.py
bowyer/node/__init__.pyx
bowyer/node/_meta/spec_bowyer_node.py
bowyer/proc/__init__.py
bowyer/proc/_meta/spec_bowyer_proc.py
bowyer/proc/mainloop.pyx
bowyer/queue/__init__.py
bowyer/queue/_meta/spec_bowyer_queue.py
bowyer/queue/multiprocessing.py
bowyer/queue/zmq_client.py
bowyer/queue/zmq_server.py
bowyer/signal/__init__.py
bowyer/signal/_meta/spec_bowyer_signal.py
bowyer/sys/__init__.py
bowyer/sys/_meta/spec_bowyer_sys.py
bowyer/test/util.py
bowyer/util/__init__.py
bowyer/util/_meta/spec_bowyer_util.py
bowyer/util/_meta/spec_bowyer_util_serialization.py
bowyer/util/serialization.py
bowyer-0.1.1.dist-info/entry_points.txt
bowyer-0.1.1.dist-info/LICENSE
bowyer-0.1.1.dist-info/WHEEL
bowyer-0.1.1.dist-info/METADATA
bowyer-0.1.1.dist-info/RECORD
