Metadata-Version: 2.1
Name: bowyer
Version: 0.1.1
Summary: Model based design for developers
License: Apache 2.0
Keywords: modelling,simulation,message,dataflow,actor,framework
Author: William Payne
Author-email: wtpayne@gmail.com
Maintainer: William Payne
Maintainer-email: wtpayne@gmail.com
Requires-Python: >=3.8,<4.0
Classifier: Development Status :: 1 - Planning
Classifier: Environment :: Console
Classifier: Environment :: No Input/Output (Daemon)
Classifier: Intended Audience :: Developers
Classifier: Intended Audience :: Information Technology
Classifier: Intended Audience :: Science/Research
Classifier: License :: OSI Approved :: Apache Software License
Classifier: License :: Other/Proprietary License
Classifier: Natural Language :: English
Classifier: Operating System :: POSIX :: Linux
Classifier: Operating System :: Unix
Classifier: Programming Language :: C
Classifier: Programming Language :: Cython
Classifier: Programming Language :: Python
Classifier: Programming Language :: Python :: 3
Classifier: Programming Language :: Python :: 3.10
Classifier: Programming Language :: Python :: 3.8
Classifier: Programming Language :: Python :: 3.9
Classifier: Topic :: Scientific/Engineering
Classifier: Topic :: Scientific/Engineering :: Artificial Intelligence
Classifier: Topic :: Scientific/Engineering :: Image Processing
Classifier: Topic :: Scientific/Engineering :: Image Recognition
Classifier: Topic :: Software Development
Classifier: Topic :: Software Development :: Embedded Systems
Classifier: Topic :: Software Development :: Libraries :: Application Frameworks
Classifier: Topic :: System
Classifier: Topic :: System :: Distributed Computing
Requires-Dist: Cython (>=0.29.26,<0.30.0)
Requires-Dist: PyYAML (>=6.0,<7.0)
Requires-Dist: click (>=8.0.3,<9.0.0)
Requires-Dist: dill (>=0.3.4,<0.4.0)
Requires-Dist: jsonschema (>=4.4.0,<5.0.0)
Requires-Dist: loguru (>=0.5.3,<0.6.0)
Requires-Dist: numpy (>=1.22.1,<2.0.0)
Requires-Dist: zmq (>=0.0.0,<0.0.1)
